[
    {
        "image_name": "img0.jpg",
        "accuracy": 1.6011028492357582e-05
    },
    {
        "image_name": "img1.jpg",
        "accuracy": 4.014204790792064e-08
    },
    {
        "image_name": "img2.jpg",
        "accuracy": 2.559983443006786e-07
    },
    {
        "image_name": "img3.jpg",
        "accuracy": 8.153039909863935e-10
    },
    {
        "image_name": "img4.jpg",
        "accuracy": 2.560607541973736e-12
    },
    {
        "image_name": "img5.jpg",
        "accuracy": 5.674577019214311e-13
    },
    {
        "image_name": "img6.jpg",
        "accuracy": 1.684415474301204e-05
    },
    {
        "image_name": "img7.jpg",
        "accuracy": 3.235538542867289e-06
    },
    {
        "image_name": "img8.jpg",
        "accuracy": 1.3508737595202547e-07
    },
    {
        "image_name": "img9.jpg",
        "accuracy": 3.694637304429982e-11
    },
    {
        "image_name": "img10.jpg",
        "accuracy": 3.990827224242821e-09
    },
    {
        "image_name": "img11.jpg",
        "accuracy": 1.5246154134729295e-06
    },
    {
        "image_name": "img12.jpg",
        "accuracy": 1.254317893994994e-08
    },
    {
        "image_name": "img13.jpg",
        "accuracy": 3.402388440432169e-11
    },
    {
        "image_name": "img14.jpg",
        "accuracy": 2.773282687940082e-07
    },
    {
        "image_name": "img15.jpg",
        "accuracy": 1.7766803306340506e-10
    },
    {
        "image_name": "img16.jpg",
        "accuracy": 2.7836128069225197e-08
    },
    {
        "image_name": "img17.jpg",
        "accuracy": 1.0627147730701836e-06
    },
    {
        "image_name": "img18.jpg",
        "accuracy": 2.9566107784262385e-08
    },
    {
        "image_name": "img19.jpg",
        "accuracy": 1.7153257658719667e-06
    },
    {
        "image_name": "img20.jpg",
        "accuracy": 1.4129037708698888e-06
    },
    {
        "image_name": "img21.jpg",
        "accuracy": 1.886369864223525e-05
    },
    {
        "image_name": "img22.jpg",
        "accuracy": 1.5878645620581722e-10
    },
    {
        "image_name": "img23.jpg",
        "accuracy": 5.582467110798461e-07
    },
    {
        "image_name": "img24.jpg",
        "accuracy": 1.6763095800342853e-08
    },
    {
        "image_name": "img25.jpg",
        "accuracy": 9.605001238810473e-09
    },
    {
        "image_name": "img26.jpg",
        "accuracy": 3.5514235996458865e-09
    },
    {
        "image_name": "img27.jpg",
        "accuracy": 2.3214454802911177e-09
    },
    {
        "image_name": "img28.jpg",
        "accuracy": 1.2311970332135047e-09
    },
    {
        "image_name": "img29.jpg",
        "accuracy": 0.008687981404364109
    },
    {
        "image_name": "img30.jpg",
        "accuracy": 1.9797034838120453e-05
    },
    {
        "image_name": "img31.jpg",
        "accuracy": 1.3934199159848504e-05
    },
    {
        "image_name": "img32.jpg",
        "accuracy": 3.4738991416816134e-07
    },
    {
        "image_name": "img33.jpg",
        "accuracy": 1.6356496157499123e-09
    },
    {
        "image_name": "img34.jpg",
        "accuracy": 2.9555474512221735e-08
    },
    {
        "image_name": "img35.jpg",
        "accuracy": 3.207012241546181e-06
    },
    {
        "image_name": "img36.jpg",
        "accuracy": 8.953452379500959e-06
    },
    {
        "image_name": "img37.jpg",
        "accuracy": 1.2256878845207098e-09
    },
    {
        "image_name": "img38.jpg",
        "accuracy": 5.477061915115655e-09
    },
    {
        "image_name": "img39.jpg",
        "accuracy": 0.0008589292992837727
    },
    {
        "image_name": "img40.jpg",
        "accuracy": 3.2471297872760374e-10
    },
    {
        "image_name": "img41.jpg",
        "accuracy": 2.692368752832408e-06
    },
    {
        "image_name": "img42.jpg",
        "accuracy": 4.148329253439442e-07
    },
    {
        "image_name": "img43.jpg",
        "accuracy": 2.648082215728209e-07
    },
    {
        "image_name": "img44.jpg",
        "accuracy": 1.338279209672777e-10
    },
    {
        "image_name": "img45.jpg",
        "accuracy": 3.477381085303932e-07
    },
    {
        "image_name": "img46.jpg",
        "accuracy": 3.9374761399812996e-05
    },
    {
        "image_name": "img47.jpg",
        "accuracy": 4.288878940883478e-08
    },
    {
        "image_name": "img48.jpg",
        "accuracy": 2.7231836341456983e-08
    },
    {
        "image_name": "img49.jpg",
        "accuracy": 7.648574135155073e-11
    },
    {
        "image_name": "img50.jpg",
        "accuracy": 1.2239504965094739e-09
    },
    {
        "image_name": "img51.jpg",
        "accuracy": 1.0929149295638152e-12
    },
    {
        "image_name": "img52.jpg",
        "accuracy": 4.706802059217807e-09
    },
    {
        "image_name": "img53.jpg",
        "accuracy": 1.0352534385305034e-09
    },
    {
        "image_name": "img54.jpg",
        "accuracy": 2.5972369144255936e-07
    },
    {
        "image_name": "img55.jpg",
        "accuracy": 9.310619475400017e-08
    },
    {
        "image_name": "img56.jpg",
        "accuracy": 9.094942470255774e-07
    },
    {
        "image_name": "img57.jpg",
        "accuracy": 5.440096706443853e-10
    },
    {
        "image_name": "img58.jpg",
        "accuracy": 6.829664611629482e-10
    },
    {
        "image_name": "img59.jpg",
        "accuracy": 2.7830554527596973e-10
    },
    {
        "image_name": "img60.jpg",
        "accuracy": 1.5935867070382415e-09
    },
    {
        "image_name": "img61.jpg",
        "accuracy": 1.1703936486640032e-08
    },
    {
        "image_name": "img62.jpg",
        "accuracy": 2.9068934281895054e-07
    },
    {
        "image_name": "img63.jpg",
        "accuracy": 1.0368721632403322e-06
    },
    {
        "image_name": "img64.jpg",
        "accuracy": 6.531089558059477e-10
    },
    {
        "image_name": "img65.jpg",
        "accuracy": 3.356574598001316e-05
    },
    {
        "image_name": "img66.jpg",
        "accuracy": 1.1615848194423961e-07
    },
    {
        "image_name": "img67.jpg",
        "accuracy": 1.6662662005728635e-07
    },
    {
        "image_name": "img68.jpg",
        "accuracy": 6.212312086972815e-07
    },
    {
        "image_name": "img69.jpg",
        "accuracy": 8.928499051208405e-10
    },
    {
        "image_name": "img70.jpg",
        "accuracy": 1.3806736309796008e-10
    },
    {
        "image_name": "img71.jpg",
        "accuracy": 1.5124200558602752e-08
    },
    {
        "image_name": "img72.jpg",
        "accuracy": 1.3442263968599377e-09
    },
    {
        "image_name": "img73.jpg",
        "accuracy": 1.3391280617724988e-07
    },
    {
        "image_name": "img74.jpg",
        "accuracy": 5.193090402144662e-10
    },
    {
        "image_name": "img75.jpg",
        "accuracy": 1.4639682799355569e-09
    },
    {
        "image_name": "img76.jpg",
        "accuracy": 3.187660695402883e-07
    },
    {
        "image_name": "img77.jpg",
        "accuracy": 6.08718542238762e-09
    },
    {
        "image_name": "img78.jpg",
        "accuracy": 1.679460001469124e-05
    },
    {
        "image_name": "img79.jpg",
        "accuracy": 1.9307944967295043e-06
    },
    {
        "image_name": "img80.jpg",
        "accuracy": 2.1409795865432596e-13
    },
    {
        "image_name": "img81.jpg",
        "accuracy": 4.5775024659633345e-07
    },
    {
        "image_name": "img82.jpg",
        "accuracy": 1.6542072600600477e-08
    },
    {
        "image_name": "img83.jpg",
        "accuracy": 2.097927342958883e-08
    },
    {
        "image_name": "img84.jpg",
        "accuracy": 4.947779643771355e-07
    },
    {
        "image_name": "img85.jpg",
        "accuracy": 8.205241783798556e-07
    },
    {
        "image_name": "img86.jpg",
        "accuracy": 1.3231144180281262e-08
    },
    {
        "image_name": "img87.jpg",
        "accuracy": 4.719302726385877e-09
    },
    {
        "image_name": "img88.jpg",
        "accuracy": 2.6474575420820656e-08
    },
    {
        "image_name": "img89.jpg",
        "accuracy": 1.2831127094159456e-07
    },
    {
        "image_name": "img90.jpg",
        "accuracy": 1.230150587616663e-06
    },
    {
        "image_name": "img91.jpg",
        "accuracy": 1.573937780108281e-08
    },
    {
        "image_name": "img92.jpg",
        "accuracy": 1.1061951354918165e-10
    },
    {
        "image_name": "img93.jpg",
        "accuracy": 4.5300902229428175e-07
    },
    {
        "image_name": "img94.jpg",
        "accuracy": 5.6157970634851395e-11
    },
    {
        "image_name": "img95.jpg",
        "accuracy": 1.4281037863383972e-07
    },
    {
        "image_name": "img96.jpg",
        "accuracy": 1.825254827281242e-07
    },
    {
        "image_name": "img97.jpg",
        "accuracy": 3.187340189469978e-05
    },
    {
        "image_name": "img98.jpg",
        "accuracy": 5.369380232878029e-06
    },
    {
        "image_name": "img99.jpg",
        "accuracy": 7.279702884943617e-08
    }
]