[
    {
        "image_name": "img0.jpg",
        "accuracy": 0.009502647444605827
    },
    {
        "image_name": "img1.jpg",
        "accuracy": 6.62660677335225e-05
    },
    {
        "image_name": "img2.jpg",
        "accuracy": 5.509755851562659e-07
    },
    {
        "image_name": "img3.jpg",
        "accuracy": 4.724230340258373e-09
    },
    {
        "image_name": "img4.jpg",
        "accuracy": 5.983342483582496e-14
    },
    {
        "image_name": "img5.jpg",
        "accuracy": 1.1586767136029241e-11
    },
    {
        "image_name": "img6.jpg",
        "accuracy": 1.1470348937336894e-07
    },
    {
        "image_name": "img7.jpg",
        "accuracy": 9.205723472405225e-05
    },
    {
        "image_name": "img8.jpg",
        "accuracy": 8.954837539931759e-05
    },
    {
        "image_name": "img9.jpg",
        "accuracy": 3.86775203878309e-12
    },
    {
        "image_name": "img10.jpg",
        "accuracy": 3.923598390631611e-10
    },
    {
        "image_name": "img11.jpg",
        "accuracy": 7.542666571680456e-05
    },
    {
        "image_name": "img12.jpg",
        "accuracy": 2.6673976094571117e-07
    },
    {
        "image_name": "img13.jpg",
        "accuracy": 2.422823115466599e-07
    },
    {
        "image_name": "img14.jpg",
        "accuracy": 6.413970550056547e-05
    },
    {
        "image_name": "img15.jpg",
        "accuracy": 7.0791332795749895e-09
    },
    {
        "image_name": "img16.jpg",
        "accuracy": 2.993876364598691e-07
    },
    {
        "image_name": "img17.jpg",
        "accuracy": 8.546355820726603e-05
    },
    {
        "image_name": "img18.jpg",
        "accuracy": 1.3719011349166976e-06
    },
    {
        "image_name": "img19.jpg",
        "accuracy": 2.6308217826453983e-08
    },
    {
        "image_name": "img20.jpg",
        "accuracy": 2.503058738057007e-07
    },
    {
        "image_name": "img21.jpg",
        "accuracy": 1.415759379597148e-05
    },
    {
        "image_name": "img22.jpg",
        "accuracy": 3.8943741564878565e-09
    },
    {
        "image_name": "img23.jpg",
        "accuracy": 6.618421934945218e-07
    },
    {
        "image_name": "img24.jpg",
        "accuracy": 9.799358373363543e-12
    },
    {
        "image_name": "img25.jpg",
        "accuracy": 2.867020221231087e-08
    },
    {
        "image_name": "img26.jpg",
        "accuracy": 6.685300099965041e-13
    },
    {
        "image_name": "img27.jpg",
        "accuracy": 5.7135835618282727e-08
    },
    {
        "image_name": "img28.jpg",
        "accuracy": 3.308781720834375e-11
    },
    {
        "image_name": "img29.jpg",
        "accuracy": 6.037271127468102e-09
    },
    {
        "image_name": "img30.jpg",
        "accuracy": 1.1964716328805025e-08
    },
    {
        "image_name": "img31.jpg",
        "accuracy": 5.5616346799070016e-06
    },
    {
        "image_name": "img32.jpg",
        "accuracy": 9.748809048915064e-08
    },
    {
        "image_name": "img33.jpg",
        "accuracy": 3.982761711540661e-07
    },
    {
        "image_name": "img34.jpg",
        "accuracy": 5.054887064481761e-10
    },
    {
        "image_name": "img35.jpg",
        "accuracy": 3.250642919283564e-07
    },
    {
        "image_name": "img36.jpg",
        "accuracy": 1.4513424906326122e-09
    },
    {
        "image_name": "img37.jpg",
        "accuracy": 5.689355653260009e-10
    },
    {
        "image_name": "img38.jpg",
        "accuracy": 1.6403947644683115e-10
    },
    {
        "image_name": "img39.jpg",
        "accuracy": 6.247202009035391e-07
    },
    {
        "image_name": "img40.jpg",
        "accuracy": 7.258262324505438e-10
    },
    {
        "image_name": "img41.jpg",
        "accuracy": 7.330309870212659e-08
    },
    {
        "image_name": "img42.jpg",
        "accuracy": 1.9912361040042015e-06
    },
    {
        "image_name": "img43.jpg",
        "accuracy": 3.6678864390182753e-09
    },
    {
        "image_name": "img44.jpg",
        "accuracy": 1.4591924673776346e-13
    },
    {
        "image_name": "img45.jpg",
        "accuracy": 3.6010808344144607e-06
    },
    {
        "image_name": "img46.jpg",
        "accuracy": 3.258996002841741e-06
    },
    {
        "image_name": "img47.jpg",
        "accuracy": 0.0009995971340686083
    },
    {
        "image_name": "img48.jpg",
        "accuracy": 5.7813981158005845e-08
    },
    {
        "image_name": "img49.jpg",
        "accuracy": 1.9325195665942374e-08
    },
    {
        "image_name": "img50.jpg",
        "accuracy": 9.29621002399017e-09
    },
    {
        "image_name": "img51.jpg",
        "accuracy": 5.003300440620251e-09
    },
    {
        "image_name": "img52.jpg",
        "accuracy": 1.271780547540402e-05
    },
    {
        "image_name": "img53.jpg",
        "accuracy": 1.3319393331323592e-12
    },
    {
        "image_name": "img54.jpg",
        "accuracy": 0.0002564801543485373
    },
    {
        "image_name": "img55.jpg",
        "accuracy": 2.6806990263139596e-06
    },
    {
        "image_name": "img56.jpg",
        "accuracy": 1.5145934639804182e-06
    },
    {
        "image_name": "img57.jpg",
        "accuracy": 1.6279297354593325e-10
    },
    {
        "image_name": "img58.jpg",
        "accuracy": 5.294089611140862e-10
    },
    {
        "image_name": "img59.jpg",
        "accuracy": 2.594304458758412e-11
    },
    {
        "image_name": "img60.jpg",
        "accuracy": 5.695845461950455e-10
    },
    {
        "image_name": "img61.jpg",
        "accuracy": 3.661151879441604e-07
    },
    {
        "image_name": "img62.jpg",
        "accuracy": 0.0008660312741994858
    },
    {
        "image_name": "img63.jpg",
        "accuracy": 3.8362331089558666e-09
    },
    {
        "image_name": "img64.jpg",
        "accuracy": 4.872220404905647e-10
    },
    {
        "image_name": "img65.jpg",
        "accuracy": 1.0418124475108925e-05
    },
    {
        "image_name": "img66.jpg",
        "accuracy": 2.3041511099108902e-07
    },
    {
        "image_name": "img67.jpg",
        "accuracy": 1.2602706656039686e-09
    },
    {
        "image_name": "img68.jpg",
        "accuracy": 9.63077695814718e-07
    },
    {
        "image_name": "img69.jpg",
        "accuracy": 8.686566133064844e-08
    },
    {
        "image_name": "img70.jpg",
        "accuracy": 5.076894904476603e-09
    },
    {
        "image_name": "img71.jpg",
        "accuracy": 3.342209765833104e-06
    },
    {
        "image_name": "img72.jpg",
        "accuracy": 7.568789328615821e-07
    },
    {
        "image_name": "img73.jpg",
        "accuracy": 1.3915123417973518e-06
    },
    {
        "image_name": "img74.jpg",
        "accuracy": 0.00010337208368582651
    },
    {
        "image_name": "img75.jpg",
        "accuracy": 7.545380292794945e-11
    },
    {
        "image_name": "img76.jpg",
        "accuracy": 3.0998188549347105e-07
    },
    {
        "image_name": "img77.jpg",
        "accuracy": 3.073780119322578e-10
    },
    {
        "image_name": "img78.jpg",
        "accuracy": 2.9876302960474277e-06
    },
    {
        "image_name": "img79.jpg",
        "accuracy": 0.005298077128827572
    },
    {
        "image_name": "img80.jpg",
        "accuracy": 5.561918113572428e-13
    },
    {
        "image_name": "img81.jpg",
        "accuracy": 7.304137739083671e-08
    },
    {
        "image_name": "img82.jpg",
        "accuracy": 6.817907706135884e-05
    },
    {
        "image_name": "img83.jpg",
        "accuracy": 5.7684722776230046e-08
    },
    {
        "image_name": "img84.jpg",
        "accuracy": 5.173253521206789e-05
    },
    {
        "image_name": "img85.jpg",
        "accuracy": 0.39480626583099365
    },
    {
        "image_name": "img86.jpg",
        "accuracy": 6.832829058112111e-06
    },
    {
        "image_name": "img87.jpg",
        "accuracy": 1.656075255596079e-05
    },
    {
        "image_name": "img88.jpg",
        "accuracy": 3.103856727193488e-09
    },
    {
        "image_name": "img89.jpg",
        "accuracy": 5.205800945873307e-08
    },
    {
        "image_name": "img90.jpg",
        "accuracy": 4.072327897119976e-07
    },
    {
        "image_name": "img91.jpg",
        "accuracy": 1.1951207135041386e-08
    },
    {
        "image_name": "img92.jpg",
        "accuracy": 1.0052969567908576e-09
    },
    {
        "image_name": "img93.jpg",
        "accuracy": 4.224749616810186e-08
    },
    {
        "image_name": "img94.jpg",
        "accuracy": 9.962567229515606e-12
    },
    {
        "image_name": "img95.jpg",
        "accuracy": 2.7128987767355284e-07
    },
    {
        "image_name": "img96.jpg",
        "accuracy": 3.284594072283653e-07
    },
    {
        "image_name": "img97.jpg",
        "accuracy": 7.401235052384436e-06
    },
    {
        "image_name": "img98.jpg",
        "accuracy": 0.0001631619961699471
    },
    {
        "image_name": "img99.jpg",
        "accuracy": 1.607267741121632e-08
    }
]